{
  "meta": {
    "generated_at": "2025-05-28T08:10:16.326820",
    "version": "3.11.0",
    "report_id": "dbef5324-0b76-4b29-a262-0f98c0659354"
  },
  "results": [
    {
      "audit_id": "42b6d5fb-8eda-425a-a258-43928faedb8c",
      "device_info": {
        "hostname": "RTR-CORE-01.xrnet.net",
        "ip": "172.16.39.100",
        "device_type": "cisco_ios"
      },
      "audit_type": "security",
      "timestamp": "2025-05-28T08:10:06.281274",
      "phases": {
        "connectivity": {
          "status": "Failed",
          "details": {
            "method": "ICMP ping (simulated)",
            "response_time_ms": null
          },
          "error": "Simulated connectivity failure"
        },
        "authentication": {
          "status": "Skipped",
          "details": {},
          "error": "Skipped due to connectivity failure"
        },
        "config_audit": {
          "status": "Skipped",
          "details": {},
          "error": "Skipped due to authentication failure"
        },
        "risk_assessment": {
          "status": "Success",
          "details": {
            "checks_performed": [
              "telnet_enabled",
              "weak_passwords",
              "unused_accounts",
              "insecure_services",
              "unsecured_interfaces"
            ],
            "issues_found": 0
          },
          "error": null
        },
        "reporting": {
          "status": "Success",
          "details": {
            "report_type": "security",
            "findings_count": 0,
            "recommendations_count": 0
          },
          "error": null
        }
      },
      "summary": {},
      "recommendations": [],
      "notes": [
        {
          "text": "This audit was conducted in TEST MODE due to connection failures with real devices.",
          "timestamp": "2025-05-28T08:10:06.281706"
        }
      ]
    },
    {
      "audit_id": "4ef68c37-89f9-4da5-894f-cea9ded2dac3",
      "device_info": {
        "hostname": "RTR-EDGE-02.xrnet.net",
        "ip": "172.16.39.101",
        "device_type": "cisco_ios"
      },
      "audit_type": "security",
      "timestamp": "2025-05-28T08:10:06.281767",
      "phases": {
        "connectivity": {
          "status": "Success",
          "details": {
            "method": "ICMP ping (simulated)",
            "response_time_ms": 15.7
          },
          "error": null
        },
        "authentication": {
          "status": "Success",
          "details": {
            "method": "SSH authentication (simulated)",
            "protocol": "SSH",
            "username": "admin"
          },
          "error": null
        },
        "config_audit": {
          "status": "Success",
          "details": {
            "commands_executed": [
              "show running-config",
              "show interfaces",
              "show version"
            ],
            "config_size_bytes": 291
          },
          "error": null
        },
        "risk_assessment": {
          "status": "Success",
          "details": {
            "checks_performed": [
              "telnet_enabled",
              "weak_passwords",
              "unused_accounts",
              "insecure_services",
              "unsecured_interfaces"
            ],
            "issues_found": 0
          },
          "error": null
        },
        "reporting": {
          "status": "Success",
          "details": {
            "report_type": "security",
            "findings_count": 0,
            "recommendations_count": 1
          },
          "error": null
        }
      },
      "summary": {},
      "recommendations": [
        {
          "text": "Implement regular security audits and monitoring",
          "severity": "medium",
          "reference": "NIST SP 800-53: CA-7"
        }
      ],
      "notes": [
        {
          "text": "This audit was conducted in TEST MODE due to connection failures with real devices.",
          "timestamp": "2025-05-28T08:10:06.282192"
        }
      ]
    },
    {
      "audit_id": "59214053-a5f5-42ce-9336-eaed21f10ff7",
      "device_info": {
        "hostname": "RTR-BRANCH-03.xrnet.net",
        "ip": "172.16.39.102",
        "device_type": "cisco_ios"
      },
      "audit_type": "security",
      "timestamp": "2025-05-28T08:10:06.282237",
      "phases": {
        "connectivity": {
          "status": "Success",
          "details": {
            "method": "ICMP ping (simulated)",
            "response_time_ms": 15.7
          },
          "error": null
        },
        "authentication": {
          "status": "Success",
          "details": {
            "method": "SSH authentication (simulated)",
            "protocol": "SSH",
            "username": "admin"
          },
          "error": null
        },
        "config_audit": {
          "status": "Success",
          "details": {
            "commands_executed": [
              "show running-config",
              "show interfaces",
              "show version"
            ],
            "config_size_bytes": 295
          },
          "error": null
        },
        "risk_assessment": {
          "status": "Success",
          "details": {
            "checks_performed": [
              "telnet_enabled",
              "weak_passwords",
              "unused_accounts",
              "insecure_services",
              "unsecured_interfaces"
            ],
            "issues_found": 0
          },
          "error": null
        },
        "reporting": {
          "status": "Success",
          "details": {
            "report_type": "security",
            "findings_count": 0,
            "recommendations_count": 1
          },
          "error": null
        }
      },
      "summary": {},
      "recommendations": [
        {
          "text": "Implement regular security audits and monitoring",
          "severity": "medium",
          "reference": "NIST SP 800-53: CA-7"
        }
      ],
      "notes": [
        {
          "text": "This audit was conducted in TEST MODE due to connection failures with real devices.",
          "timestamp": "2025-05-28T08:10:06.282979"
        }
      ]
    },
    {
      "audit_id": "c4ee15d8-5c55-4892-b50f-801c0e010572",
      "device_info": {
        "hostname": "RTR-BRANCH-04.xrnet.net",
        "ip": "172.16.39.103",
        "device_type": "cisco_ios"
      },
      "audit_type": "security",
      "timestamp": "2025-05-28T08:10:06.283093",
      "phases": {
        "connectivity": {
          "status": "Success",
          "details": {
            "method": "ICMP ping (simulated)",
            "response_time_ms": 15.7
          },
          "error": null
        },
        "authentication": {
          "status": "Success",
          "details": {
            "method": "SSH authentication (simulated)",
            "protocol": "SSH",
            "username": "admin"
          },
          "error": null
        },
        "config_audit": {
          "status": "Success",
          "details": {
            "commands_executed": [
              "show running-config",
              "show interfaces",
              "show version"
            ],
            "config_size_bytes": 295
          },
          "error": null
        },
        "risk_assessment": {
          "status": "Success",
          "details": {
            "checks_performed": [
              "telnet_enabled",
              "weak_passwords",
              "unused_accounts",
              "insecure_services",
              "unsecured_interfaces"
            ],
            "issues_found": 0
          },
          "error": null
        },
        "reporting": {
          "status": "Success",
          "details": {
            "report_type": "security",
            "findings_count": 0,
            "recommendations_count": 1
          },
          "error": null
        }
      },
      "summary": {},
      "recommendations": [
        {
          "text": "Implement regular security audits and monitoring",
          "severity": "medium",
          "reference": "NIST SP 800-53: CA-7"
        }
      ],
      "notes": [
        {
          "text": "This audit was conducted in TEST MODE due to connection failures with real devices.",
          "timestamp": "2025-05-28T08:10:06.284035"
        }
      ]
    },
    {
      "audit_id": "5342799c-b464-41b5-bc39-966587877e49",
      "device_info": {
        "hostname": "RTR-BRANCH-05.xrnet.net",
        "ip": "172.16.39.104",
        "device_type": "cisco_ios"
      },
      "audit_type": "security",
      "timestamp": "2025-05-28T08:10:06.284121",
      "phases": {
        "connectivity": {
          "status": "Success",
          "details": {
            "method": "ICMP ping (simulated)",
            "response_time_ms": 15.7
          },
          "error": null
        },
        "authentication": {
          "status": "Success",
          "details": {
            "method": "SSH authentication (simulated)",
            "protocol": "SSH",
            "username": "admin"
          },
          "error": null
        },
        "config_audit": {
          "status": "Success",
          "details": {
            "commands_executed": [
              "show running-config",
              "show interfaces",
              "show version"
            ],
            "config_size_bytes": 295
          },
          "error": null
        },
        "risk_assessment": {
          "status": "Success",
          "details": {
            "checks_performed": [
              "telnet_enabled",
              "weak_passwords",
              "unused_accounts",
              "insecure_services",
              "unsecured_interfaces"
            ],
            "issues_found": 0
          },
          "error": null
        },
        "reporting": {
          "status": "Success",
          "details": {
            "report_type": "security",
            "findings_count": 0,
            "recommendations_count": 1
          },
          "error": null
        }
      },
      "summary": {},
      "recommendations": [
        {
          "text": "Implement regular security audits and monitoring",
          "severity": "medium",
          "reference": "NIST SP 800-53: CA-7"
        }
      ],
      "notes": [
        {
          "text": "This audit was conducted in TEST MODE due to connection failures with real devices.",
          "timestamp": "2025-05-28T08:10:06.285139"
        }
      ]
    },
    {
      "audit_id": "35d7d8c0-83bd-4a0c-9e92-08f3841743e8",
      "device_info": {
        "hostname": "RTR-BRANCH-06.xrnet.net",
        "ip": "172.16.39.105",
        "device_type": "cisco_ios"
      },
      "audit_type": "security",
      "timestamp": "2025-05-28T08:10:06.285220",
      "phases": {
        "connectivity": {
          "status": "Success",
          "details": {
            "method": "ICMP ping (simulated)",
            "response_time_ms": 15.7
          },
          "error": null
        },
        "authentication": {
          "status": "Success",
          "details": {
            "method": "SSH authentication (simulated)",
            "protocol": "SSH",
            "username": "admin"
          },
          "error": null
        },
        "config_audit": {
          "status": "Success",
          "details": {
            "commands_executed": [
              "show running-config",
              "show interfaces",
              "show version"
            ],
            "config_size_bytes": 295
          },
          "error": null
        },
        "risk_assessment": {
          "status": "Success",
          "details": {
            "checks_performed": [
              "telnet_enabled",
              "weak_passwords",
              "unused_accounts",
              "insecure_services",
              "unsecured_interfaces"
            ],
            "issues_found": 0
          },
          "error": null
        },
        "reporting": {
          "status": "Success",
          "details": {
            "report_type": "security",
            "findings_count": 0,
            "recommendations_count": 1
          },
          "error": null
        }
      },
      "summary": {},
      "recommendations": [
        {
          "text": "Implement regular security audits and monitoring",
          "severity": "medium",
          "reference": "NIST SP 800-53: CA-7"
        }
      ],
      "notes": [
        {
          "text": "This audit was conducted in TEST MODE due to connection failures with real devices.",
          "timestamp": "2025-05-28T08:10:06.285896"
        }
      ]
    },
    {
      "audit_id": "9ffbcb18-4174-449a-9eab-5dcd6f029f20",
      "device_info": {
        "hostname": "RTR-BRANCH-05.xrnet.net",
        "ip": "172.16.39.104",
        "model": "Cisco 2911 Integrated Services Router",
        "device_type": "cisco_ios"
      },
      "audit_type": "telnet",
      "timestamp": "2025-05-28T08:10:06.304243",
      "phases": {
        "connection": {
          "status": "Failed",
          "details": {
            "method": "SSH"
          },
          "error": "Connection timed out"
        }
      },
      "summary": {},
      "recommendations": [],
      "notes": []
    },
    {
      "audit_id": "90494ccf-d260-46c8-91dd-d3a9a6762ea3",
      "device_info": {
        "hostname": "RTR-BRANCH-04.xrnet.net",
        "ip": "172.16.39.103",
        "model": "Cisco 4321 Integrated Services Router",
        "device_type": "cisco_ios"
      },
      "audit_type": "telnet",
      "timestamp": "2025-05-28T08:10:06.307811",
      "phases": {
        "connection": {
          "status": "Failed",
          "details": {
            "method": "SSH"
          },
          "error": "Connection timed out"
        }
      },
      "summary": {},
      "recommendations": [],
      "notes": []
    },
    {
      "audit_id": "9e0177c7-b601-4564-bd5e-3896b0b86956",
      "device_info": {
        "hostname": "RTR-BRANCH-06.xrnet.net",
        "ip": "172.16.39.105",
        "model": "Cisco 2911 Integrated Services Router",
        "device_type": "cisco_ios"
      },
      "audit_type": "telnet",
      "timestamp": "2025-05-28T08:10:09.367824",
      "phases": {
        "connection": {
          "status": "Failed",
          "details": {
            "method": "SSH"
          },
          "error": "Connection timed out"
        }
      },
      "summary": {},
      "recommendations": [],
      "notes": []
    },
    {
      "audit_id": "b6d7bfd1-77d9-4ac3-8183-6cf75307fea3",
      "device_info": {
        "hostname": "RTR-CORE-01.xrnet.net",
        "ip": "172.16.39.100",
        "model": "Cisco 4431 Integrated Services Router",
        "device_type": "cisco_ios"
      },
      "audit_type": "telnet",
      "timestamp": "2025-05-28T08:10:06.298996",
      "phases": {
        "connection": {
          "status": "Failed",
          "details": {
            "method": "SSH"
          },
          "error": "Connection timed out"
        }
      },
      "summary": {},
      "recommendations": [],
      "notes": []
    },
    {
      "audit_id": "5c2d453f-4dd1-4e6d-b24f-30f74fd59446",
      "device_info": {
        "hostname": "RTR-EDGE-02.xrnet.net",
        "ip": "172.16.39.101",
        "model": "Cisco 4451-X Integrated Services Router",
        "device_type": "cisco_ios"
      },
      "audit_type": "telnet",
      "timestamp": "2025-05-28T08:10:06.300489",
      "phases": {
        "connection": {
          "status": "Failed",
          "details": {
            "method": "SSH"
          },
          "error": "Connection timed out"
        }
      },
      "summary": {},
      "recommendations": [],
      "notes": []
    },
    {
      "audit_id": "ec4e0b43-8200-4452-a0dd-a6f033656da7",
      "device_info": {
        "hostname": "RTR-BRANCH-03.xrnet.net",
        "ip": "172.16.39.102",
        "model": "Cisco 3945 Integrated Services Router",
        "device_type": "cisco_ios"
      },
      "audit_type": "telnet",
      "timestamp": "2025-05-28T08:10:06.303319",
      "phases": {
        "connection": {
          "status": "Failed",
          "details": {
            "method": "SSH"
          },
          "error": "Connection timed out"
        }
      },
      "summary": {},
      "recommendations": [],
      "notes": []
    }
  ]
}